pipns/__init__.py
pipns/__main__.py
pipns/scripts/package_files.py
pipns-0.0.12.dist-info/LICENSE
pipns-0.0.12.dist-info/METADATA
pipns-0.0.12.dist-info/WHEEL
pipns-0.0.12.dist-info/entry_points.txt
pipns-0.0.12.dist-info/top_level.txt
pipns-0.0.12.dist-info/RECORD
